timxfriend/CA.py
timxfriend/PCA.py
timxfriend/__init__.py
timxfriend/plot.py
timxfriend/svd.py
timxfriend/test.py
timxfriend/util.py
timxfriend-0.7.8.dist-info/LICENSE.txt
timxfriend-0.7.8.dist-info/METADATA
timxfriend-0.7.8.dist-info/WHEEL
timxfriend-0.7.8.dist-info/top_level.txt
timxfriend-0.7.8.dist-info/RECORD
