Metadata-Version: 2.1
Name: timxfriend
Version: 0.7.8
Summary: TYPE YOUR DESCRIPTION HERE
Home-page: https://github.com/user/reponame
Download-URL: https://github.com/user/reponame/archive/v_01.tar.gz
Author: YOUR NAME
Author-email: your.email@domain.com
License: MIT
Keywords: SOME,MEANINGFULL,KEYWORDS
Classifier: Development Status :: 3 - Alpha
Classifier: Intended Audience :: Developers
Classifier: Topic :: Software Development :: Build Tools
Classifier: License :: OSI Approved :: MIT License
Classifier: Programming Language :: Python :: 3
Classifier: Programming Language :: Python :: 3.4
Classifier: Programming Language :: Python :: 3.5
Classifier: Programming Language :: Python :: 3.6
License-File: LICENSE.txt
Requires-Dist: validators
Requires-Dist: beautifulsoup4
